{
	"list": [
		{
			"id": 25,
			"startDate": "2025-02-06T03:00:00.000Z",
			"startDateForUI": "2025-02-06T03:00:00.000Z",
			"endDate": "9999-01-01T00:00:00.000Z",
			"endDateForUI": "9999-01-01T00:00:00.000Z",
			"gracePeriod": "9999-01-01T00:00:00.000Z",
			"unlockCondition": {
				"unlockCode": 102
			},
			"eventRewardDatas": [
				{
					"rewardId": 1,
					"rewardPrice": {
						"type": "ITEM",
						"id": 1,
						"num": 20
					},
					"rewardItemList": [
						{
							"type": "ITEM",
							"id": 20026,
							"num": 10
						}
					],
					"limitCount": 500,
					"purchaseRestriction": {
						"type": "DEDUCT_PER_OWNED_ITEMS",
						"values": ["20026", "0.1"]
					}
				}
			],
			"eventMainItemId": 20026
		}
	]
}